{
  "title": "FRS 1986-01-31",
  "url": "https://fridayrockshow.fandom.com/wiki/31_January_1986",
  "show": {
    "date": "1986-01-31",
    "comments": [
      "Information of tracklisting from Hal C F Astell's website."
    ]
  },
  "sessions": [
    {
      "artist": "Spider",
      "details": "one and only. Recorded: 1986-01-10. No known commercial release."
    },
    {
      "artist": "Iron Maiden",
      "details": "one and only. Recorded: 1979-11-14. First TX: 14 December 1979. Available on BBC Archives (EMI)"
    }
  ],
  "track_listing": [
    {
      "artist": "Molly Hatchet",
      "track": "Boogie No More",
      "details": "2xLP-Double Trouble Live; Epic"
    },
    {
      "artist": "Fastway",
      "track": "The World Waits For You",
      "details": "7\"; CBS"
    },
    {
      "artist": "Spider",
      "track": "Mind, Heart, Body And Soul",
      "details": "FRS Session"
    },
    {
      "artist": "Jade",
      "track": "'If You're Man Enough (LP-If You're Man Enough)' (Roadrunner)",
      "details": null
    },
    {
      "artist": "ZZ Top",
      "track": "Stages",
      "details": "7\"; Warner Bros."
    },
    {
      "artist": "Kiss",
      "track": "King Of The Night Time World",
      "details": "LP-Destroyer; Casablanca"
    },
    {
      "artist": "Iron Maiden",
      "track": "Iron Maiden",
      "details": "FRS Session"
    },
    {
      "artist": "Iron Maiden",
      "track": "Running Free",
      "details": "FRS Session"
    },
    {
      "artist": "Spider",
      "track": "Gimme Gimme Gimme It All",
      "details": "FRS Session"
    },
    {
      "artist": "Seducer",
      "track": "'Don't Fall In Love (Rock 'N' Roll) (LP-Caught In The Act)' (Thunderbolt)",
      "details": null
    },
    {
      "artist": "Mötley Crüe",
      "track": "'Smokin' In The Boys Room (CD-Theatre Of Pain)' (Elektra)",
      "details": null
    },
    {
      "artist": "Cherry Bombz",
      "track": "Hot Girls In Love",
      "details": "12\"; Lick"
    },
    {
      "artist": null,
      "track": "Lie Back And Enjoy It",
      "details": null
    },
    {
      "artist": "Spider",
      "track": "'I'm Not The Only One'",
      "details": "FRS Session"
    },
    {
      "artist": "Peter Frampton",
      "track": "Moving A Mountain",
      "details": "LP-Premonition; Virgin"
    },
    {
      "artist": "Iron Maiden",
      "track": "Transylvania",
      "details": "FRS Session"
    },
    {
      "artist": "Iron Maiden",
      "track": "Sanctuary",
      "details": "FRS Session"
    },
    {
      "artist": "Vow Wow",
      "track": "Shake Your Body",
      "details": "LP-Cyclone; East Rock"
    },
    {
      "artist": "Marillion",
      "track": "Charting The Single",
      "details": "7\"-He Knows You Know; EMI"
    },
    {
      "artist": "Spider",
      "track": "Need To Know About You",
      "details": "FRS Session"
    },
    {
      "artist": "Rush",
      "track": "'Countdown (LP-Signals)' (Mercury) Last-minute addition to the show as a tribute to the Space Shuttle Challenger disaster on January 28.",
      "details": null
    }
  ]
}