{
  "title": "FRS 1990-04-06",
  "url": "https://fridayrockshow.fandom.com/wiki/06_April_1990",
  "show": {
    "date": "1990-04-06",
    "comments": [
      "Information of tracklisting from Hal C F Astell's website.",
      "Tommy is knocked out by Robert Plant's new album, Manic Nirvana, and features a further track from it.",
      "Interview with Bruce Dickinson, ahead of his debut solo album.",
      "The Rock War features First Born from Hereford, Quit Bitching from Toxteth and Artisan from East Yorkshire. Artisan won, with Quit Bitching second and First Born third.",
      "Tommy mentions that there will be no Rock War the following week as he'll be broadcasting live from the Newcastle Mayfair (this was to mark the belated arrival of Radio 1 on FM throughout north-east England, a renowned hard rock and metal heartland). Before the Friday Night Connection and at the end of the show, he mentions that the two bands will be Romeo's Daughter and Thunder.",
      "After the Rock War, there's an advert for the Nelson Mandela Tribute Concert on Easter Monday, two months after his release. That was 16 Apr 1990 (for the highly questionable handling of the event by Radio 1, see Andy Kershaw's comments in The Nation's Favourite).",
      "Friday Night Connection from Bruce Maclean of Sheffield, who got the previous connection. Those selections were from Steve Smith from Burton-on-Trent: Manowar's March for Revenge, April Wine's Anything You Want, You Got It and Uriah Heep's July Morning."
    ]
  },
  "sessions": [
    {
      "artist": "Dawn Patrol",
      "details": "Recorded: 1990-03-23"
    }
  ],
  "track_listing": [
    {
      "artist": null,
      "track": "Heart - Wild Child",
      "details": null
    },
    {
      "artist": null,
      "track": "Robert Plant - Hurting Kind",
      "details": null
    },
    {
      "artist": null,
      "track": "Bruce Dickinson - Tattooed Millionaire",
      "details": null
    },
    {
      "artist": null,
      "track": "Bruce Dickinson - Dive! Dive! Dive!",
      "details": null
    },
    {
      "artist": null,
      "track": "Bruce Dickinson - Zulu Lulu",
      "details": null
    },
    {
      "artist": null,
      "track": "Soundgarden - Hands All Over",
      "details": null
    },
    {
      "artist": null,
      "track": "First Born - Living a Lie (Rock War act)",
      "details": null
    },
    {
      "artist": null,
      "track": "Quit Bitchin - Don't Stop Me (Rock War act)",
      "details": null
    },
    {
      "artist": null,
      "track": "Artisan - Reach Out (Rock War act)",
      "details": null
    },
    {
      "artist": null,
      "track": "Kiss - Forever",
      "details": null
    },
    {
      "artist": null,
      "track": "Damn Yankees - Come Again",
      "details": null
    },
    {
      "artist": null,
      "track": "Dawn Patrol - Slight of Heart (FRS session)",
      "details": null
    },
    {
      "artist": null,
      "track": "Dawn Patrol - Shades of Grey (FRS session)",
      "details": null
    },
    {
      "artist": null,
      "track": "Friday Night Connection",
      "details": null
    },
    {
      "artist": null,
      "track": "Joe Satriani - Big Bad Moon",
      "details": null
    },
    {
      "artist": null,
      "track": "Tora Tora - She's Good She's Bad",
      "details": null
    },
    {
      "artist": null,
      "track": "Dawn Patrol - Private Dancer (FRS session)",
      "details": null
    },
    {
      "artist": null,
      "track": "Dawn Patrol - Explicit Through Implication (FRS session)",
      "details": null
    },
    {
      "artist": null,
      "track": "Love/Hate - Blackout in the Red Room",
      "details": null
    },
    {
      "artist": null,
      "track": "Gillan - Mad Elaine",
      "details": null
    }
  ]
}