{
  "title": "FRS 1992-08-28",
  "url": "https://fridayrockshow.fandom.com/wiki/28_August_1992",
  "show": {
    "date": "1992-08-28",
    "comments": [
      "Rock War, Round 8, Heat 3 features Empyr (from West Sussex); Mad Hatter (Torquay); and Chain (London).",
      "Artists trailed but not featured on the available recording: Damn Yankees, Thunder, Asia and Danzig."
    ]
  },
  "sessions": [],
  "track_listing": [
    {
      "artist": "Metal Church",
      "track": "Watch The Children Pray",
      "details": "LP-The Dark; Elektra"
    },
    {
      "artist": "Rollins Band",
      "track": "Tearing (edit) 7\")",
      "details": "Imago"
    },
    {
      "artist": null,
      "track": "trailer for 1FM Party In The Park, Sutton Park, Birmingham",
      "details": null
    },
    {
      "artist": "Skew Siskin",
      "track": "If The Walls Could Talk",
      "details": "LP-Skew Siskin; Giant"
    },
    {
      "artist": "Warrant",
      "track": "The Whole In My Wall",
      "details": "CD-Dog Eat Dog; Columbia"
    },
    {
      "artist": "My Little Funhouse",
      "track": "Standunder",
      "details": "12\"-Addicted; Geffen"
    },
    {
      "artist": "Black Crowes",
      "track": "Sting Me",
      "details": "CDS1; Def American Recordings"
    },
    {
      "artist": null,
      "track": "BBC Radio 1 News @ 9.30 read by Jane Markham",
      "details": null
    },
    {
      "artist": null,
      "track": "TV counts down the top 30 rock/metal singles chart",
      "details": null
    },
    {
      "artist": "Ugly Kid Joe",
      "track": "Neighbor",
      "details": "7\"; Mercury"
    },
    {
      "artist": "Iron Maiden",
      "track": "Holy Smoke",
      "details": "7\"; EMI"
    },
    {
      "artist": "Status Quo",
      "track": "Big Fat Mama",
      "details": "LP-Piledriver; Vertigo"
    },
    {
      "artist": "L7",
      "track": "Monster",
      "details": "7\"; Slash/London"
    },
    {
      "artist": "Vince Neil",
      "track": "'You're Invited (But Your Friend Can't Come) (7\")' (Hollywood)",
      "details": null
    }
  ]
}