{
  "title": "FRS 1980-05-09",
  "url": "https://fridayrockshow.fandom.com/wiki/09_May_1980",
  "show": {
    "date": "1980-05-09",
    "comments": [
      "Tony Wilson \"Goodnight!\""
    ]
  },
  "sessions": [
    {
      "artist": "Rush",
      "details": "recorded at Pink Pop Festival 1979"
    }
  ],
  "track_listing": [
    {
      "artist": "Judas Priest",
      "track": "Victim Of Changes",
      "details": "LP-Unleashed In The East"
    },
    {
      "artist": "Angel",
      "track": "'Don't Leave Me Lonely'",
      "details": "LP-Live Without A Net"
    },
    {
      "artist": "Axe",
      "track": "Sympathise",
      "details": "LP-Axe"
    },
    {
      "artist": "Gillan",
      "track": "Mr Universe",
      "details": "LP-Mr Universe"
    },
    {
      "artist": "Magazine",
      "track": "Thank You",
      "details": "Falettinme Be Mice Elf Agin; LP-The Correct Use Of Soap"
    },
    {
      "artist": "Alice Cooper",
      "track": "Pain",
      "details": "LP-Flush The Fashion"
    },
    {
      "artist": "AC/DC",
      "track": "Whole Lotta Rosie",
      "details": "LP-If You Want Blood You've Got It"
    },
    {
      "artist": "Geordie",
      "track": "'She's A Lady'",
      "details": "LP-Save The World"
    },
    {
      "artist": "Roy Harper",
      "track": "You",
      "details": "The Game Part II; LP-The Unknown Soldier"
    },
    {
      "artist": "Roger Powell",
      "track": "Prophecy",
      "details": "LP-Air Pocket"
    },
    {
      "artist": null,
      "track": "Friday Night Connection",
      "details": null
    },
    {
      "artist": "Rush",
      "track": "- Pink Pop Festival 1979",
      "details": null
    },
    {
      "artist": "Thin Lizzy",
      "track": "Chinatown",
      "details": "7\" Single ; Vertigo"
    }
  ]
}