{
  "title": "FRS 1985-11-01",
  "url": "https://fridayrockshow.fandom.com/wiki/01_November_1985",
  "show": {
    "date": "1985-11-01",
    "comments": []
  },
  "sessions": [
    {
      "artist": "Venom",
      "details": "one and only (rpt). Recorded: 1985-08-02. Available on Black Metal, remastered reissue (Castle Music)."
    },
    {
      "artist": "Tara Zara",
      "details": "one and only session (rpt). Recorded: 1985-06-07. No known commercial release. 'The Time Is Right' not TX in this show."
    }
  ],
  "track_listing": [
    {
      "artist": "Warlock",
      "track": "All Night",
      "details": "LP-Hellbound; Vertigo"
    },
    {
      "artist": "Venom",
      "track": "Nightmare",
      "details": "FRS Session"
    },
    {
      "artist": "Starship",
      "track": "We Built This City",
      "details": "CD-Knee Deep In The Hoopla; Grunt"
    },
    {
      "artist": "Far Corporation",
      "track": "Stairway To Heaven",
      "details": "7\"; IMP"
    },
    {
      "artist": "Tara Zara",
      "track": "Behind The Mask",
      "details": "FRS Session"
    },
    {
      "artist": "Mercyful Fate",
      "track": "'A Dangerous Meeting (CD-Don't Break The Oath)' (Roadrunner)",
      "details": null
    },
    {
      "artist": "Rush",
      "track": "Marathon",
      "details": "CD-Power Windows; Mercury"
    },
    {
      "artist": "Joe Lynn Turner",
      "track": "Get Tough",
      "details": "LP-Rescue You; Elektra"
    },
    {
      "artist": "Venom",
      "track": "Black Metal",
      "details": "FRS Session"
    },
    {
      "artist": "Iron Maiden",
      "track": "Phantom Of The Opera",
      "details": "LP-Iron Maiden; EMI"
    },
    {
      "artist": "Cheap Trick",
      "track": "How About You",
      "details": "LP-Standing On The Edge; Epic"
    },
    {
      "artist": "Tara Zara",
      "track": "Wake Up",
      "details": "FRS Session"
    },
    {
      "artist": "Gerry Laffy's Matrix",
      "track": "'Search And Destroy' The source of this is unknown: according to lister, \"while Tommy says it hasn't been released 'yet', maybe it never was.\"",
      "details": null
    },
    {
      "artist": "Mad Max",
      "track": "Love Chains",
      "details": "LP-Stormchild; Roadrunner"
    },
    {
      "artist": "Venom",
      "track": "Bloodlust",
      "details": "FRS Session"
    },
    {
      "artist": "Dio",
      "track": "Holy Diver",
      "details": "LP-Holy Diver; Vertigo"
    },
    {
      "artist": "ZZ Top",
      "track": "Planet Of Women",
      "details": "CD-Afterburner; Warner Bros."
    },
    {
      "artist": "Steely Dan",
      "track": "Haitian Divorce",
      "details": "CD-The Royal Scam; MCA"
    },
    {
      "artist": null,
      "track": "Lie Back And Enjoy It File c",
      "details": null
    },
    {
      "artist": "Venom",
      "track": "Too Loud For The Crowd",
      "details": "FRS Session"
    },
    {
      "artist": "Tara Zara",
      "track": "Hold Me Tonight",
      "details": "FRS Session"
    }
  ]
}